<?xml version="1.0" encoding="utf-8"?>
<document>
  <properties>
    <title>Changes Ingrid iPlug WFS (ingrid-iplug-wfs-dsc)</title>
    <author email="joachim@wemove.com">Joachim Müller</author>
  </properties>
  <body>
    <release version="3.4.0-SNAPSHOT" date="2013-xx-xx" description="Release InGrid 3.4.0-SNAPSHOT">
      <action type="add" dev="wemove" issue="AF-00186">
      	Added mapping and configuration for ZDM-WFS.
      	Added paging mechanism for fetching features.
      	Make fetching more robust to ignore malformed features !
      </action>
      <action type="update" dev="wemove" issue="INGRID-2246">
        Use german analyzer when creating/searching lucene index, now configured via XML.
        Also fix encoding of umlaute in request parameters (test search with umlaute works now in admin-gui).
      </action>
    </release>

    <release version="3.3.0" date="2013-03-13" description="Release InGrid 3.3">
      <action type="add">
        Initial release.
      </action>
    </release>
  </body>
</document>